cross_platform/__init__.py
cross_platform/linux_integration.py
cross_platform/macos_integration.py
cross_platform/windows_integration.py
ocr_document_converter-3.1.0.dist-info/licenses/LICENSE
ocr_engine/__init__.py
ocr_engine/error_handler.py
ocr_engine/format_detector.py
ocr_engine/image_processor.py
ocr_engine/memory_processor.py
ocr_engine/ocr_engine.py
ocr_engine/ocr_engine_minimal.py
ocr_engine/ocr_integration.py
ocr_engine/security.py
ocr_document_converter-3.1.0.dist-info/METADATA
ocr_document_converter-3.1.0.dist-info/WHEEL
ocr_document_converter-3.1.0.dist-info/entry_points.txt
ocr_document_converter-3.1.0.dist-info/top_level.txt
ocr_document_converter-3.1.0.dist-info/RECORD
