Metadata-Version: 2.4
Name: ocr-document-converter
Version: 3.1.0
Summary: Enterprise-grade OCR and document conversion tool with dual OCR engines
Home-page: https://github.com/Beaulewis1977/quick_ocr_doc_converter
Author: Beau Lewis
Author-email: Beau Lewis <blewisxx@gmail.com>
License: MIT
Project-URL: Homepage, https://github.com/Beaulewis1977/quick_ocr_doc_converter
Project-URL: Documentation, https://github.com/Beaulewis1977/quick_ocr_doc_converter/blob/main/OCR_README.md
Project-URL: Repository, https://github.com/Beaulewis1977/quick_ocr_doc_converter
Project-URL: Issues, https://github.com/Beaulewis1977/quick_ocr_doc_converter/issues
Keywords: ocr,document,conversion,pdf,tesseract,easyocr
Classifier: Development Status :: 5 - Production/Stable
Classifier: Intended Audience :: End Users/Desktop
Classifier: Intended Audience :: Developers
Classifier: Topic :: Text Processing :: General
Classifier: Topic :: Multimedia :: Graphics :: Capture :: Digital Camera
Classifier: Topic :: Office/Business
Classifier: License :: OSI Approved :: MIT License
Classifier: Programming Language :: Python :: 3
Classifier: Programming Language :: Python :: 3.8
Classifier: Programming Language :: Python :: 3.9
Classifier: Programming Language :: Python :: 3.10
Classifier: Programming Language :: Python :: 3.11
Classifier: Programming Language :: Python :: 3.12
Classifier: Operating System :: OS Independent
Requires-Python: >=3.8
License-File: LICENSE
Dynamic: author
Dynamic: home-page
Dynamic: license-file
Dynamic: requires-python
